[
  {"type": "function", "function": {
    "name": "code_run",
    "description": "Code executor. Prefer python. Multi-call OK, use script param. Reply code block is executed if no script arg; prefer for single call to avoid escaping. No hardcoding bulk data",
    "parameters": {"type": "object", "properties": {
      "script": {"type": "string", "description": "[Mutually exclusive] NEVER use this param when use reply code block."},
      "type": {"type": "string", "enum": ["python", "powershell"], "description": "Code type", "default": "python"},
      "timeout": {"type": "integer", "description": "in seconds", "default": 60},
      "cwd": {"type": "string", "description": "Working directory, defaults to cwd"},
      "inline_eval": {"type": "boolean", "description": "DO NOT USE except explicitly specified."}}}
  }},
  {"type": "function", "function": {
    "name": "file_read",
    "description": "Read file. Read before modify for latest context and line numbers",
    "parameters": {"type": "object", "properties": {
      "path": {"type": "string", "description": "Relative or absolute"},
      "start": {"type": "integer", "description": "Start line number (1-based)"},
      "count": {"type": "integer", "description": "Number of lines to read", "default": 600},
      "keyword": {"type": "string", "description": "[Optional] If provided, returns first match (case-insensitive) with context"},
      "show_linenos": {"type": "boolean", "description": "Show line numbers", "default": true}}}
  }},
  {"type": "function", "function": {
    "name": "file_patch",
    "description": "Replace unique old_content with new_content. Exact match required (whitespace/indentation). On failure, file_read to recheck",
    "parameters": {"type": "object", "properties": {
      "path": {"type": "string", "description": "File path"},
      "old_content": {"type": "string", "description": "Original text block to replace (must be unique)"},
      "new_content": {"type": "string", "description": "New content. Supports {{file:path:startLine:endLine}} to ref file lines, auto-expanded"}}}
  }},
  {"type": "function", "function": {
    "name": "file_write",
    "description": "Create/overwrite/append files. HUGE edits ONLY. Supports {{file:path:startLine:endLine}}, auto-expanded",
    "parameters": {"type": "object", "properties": {
      "path": {"type": "string", "description": "File path"},
      "content": {"type": "string"},
      "mode": {"type": "string", "enum": ["overwrite", "append", "prepend"], "description": "Write mode", "default": "overwrite"}}}
  }},
  {"type": "function", "function": {
    "name": "web_scan",
    "description": "Get simplified HTML and tab list. Removes hidden/floating/covered elements. Call after switching pages",
    "parameters": {"type": "object", "properties": {
      "tabs_only": {"type": "boolean"},
      "switch_tab_id": {"type": "string"},
      "text_only": {"type": "boolean"}}}
  }},
  {"type": "function", "function": {
    "name": "web_execute_js",
    "description": "Execute JS. Multi-call OK. Execute JS in ```javascript blocks if no script arg",
    "parameters": {"type": "object", "properties": {
      "script": {"type": "string"},
      "save_to_file": {"type": "string"},
      "no_monitor": {"type": "boolean"},
      "switch_tab_id": {"type": "string"}}}
  }},
  {"type": "function", "function": {
    "name": "update_working_checkpoint",
    "description": "Short-term working notepad, auto-injected each turn to prevent info loss in long tasks",
    "parameters": {"type": "object", "properties": {
      "key_info": {"type": "string"},
      "related_sop": {"type": "string"}}}
  }},
  {"type": "function", "function": {
    "name": "ask_user",
    "description": "Interrupt task to ask user when needing decisions, extra info, or facing unresolvable blockers",
    "parameters": {"type": "object", "properties": {
      "question": {"type": "string"},
      "candidates": {"type": "array", "items": {"type": "string"}}}}
  }},
  {"type": "function", "function": {
    "name": "start_long_term_update",
    "description": "Start distilling long-term memory. Must call when a task took 15+ turns is completed",
    "parameters": {"type": "object", "properties": {}}}
  }
]
